net_gsd/__init__.py
net_gsd/connections/__init__.py
net_gsd/connections/base.py
net_gsd/connections/ssh.py
net_gsd/host/__init__.py
net_gsd/host/errors.py
net_gsd/host/host.py
net_gsd/runner/__init__.py
net_gsd/runner/credentials.py
net_gsd/runner/errors.py
net_gsd/runner/runner.py
net_gsd/task/__init__.py
net_gsd/task/task.py
net_gsd-0.1.3.dist-info/WHEEL
net_gsd-0.1.3.dist-info/METADATA
net_gsd-0.1.3.dist-info/RECORD
